llama_index/readers/pinecone/__init__.py
llama_index/readers/pinecone/base.py
llama_index_readers_pinecone-0.1.4.dist-info/METADATA
llama_index_readers_pinecone-0.1.4.dist-info/WHEEL
llama_index_readers_pinecone-0.1.4.dist-info/RECORD
