Metadata-Version: 2.1
Name: llama-index-readers-pinecone
Version: 0.1.4
Summary: llama-index readers pinecone integration
License: MIT
Author: Your Name
Author-email: you@example.com
Maintainer: jerryjliu
Requires-Python: >=3.8.1,<3.13
Classifier: License :: OSI Approved :: MIT License
Classifier: Programming Language :: Python :: 3
Classifier: Programming Language :: Python :: 3.9
Classifier: Programming Language :: Python :: 3.10
Classifier: Programming Language :: Python :: 3.11
Classifier: Programming Language :: Python :: 3.12
Requires-Dist: llama-index-core (>=0.10.11.post1,<0.11.0)
Requires-Dist: pinecone-client (>=3.0.2,<4.0.0)
